cake/__init__.py
cake/__main__.py
cli_cake-0.0.3.dist-info/LICENSE
cli_cake-0.0.3.dist-info/METADATA
cli_cake-0.0.3.dist-info/WHEEL
cli_cake-0.0.3.dist-info/top_level.txt
cli_cake-0.0.3.dist-info/RECORD
