Metadata-Version: 2.1
Name: cli-cake
Version: 0.0.3
Summary: Turn your python functions into CLI-friendly scripts.
Home-page: https://github.com/mattjfan/cli-cake
Author: Matthew Fan
Author-email: mfan@umd.edu
License: UNKNOWN
Platform: UNKNOWN
Classifier: Programming Language :: Python :: 3
Classifier: License :: OSI Approved :: MIT License
Classifier: Operating System :: OS Independent
Requires-Python: >=3.6
